LICENSE
MANIFEST.in
README.md
setup.py
fastsnmp/__init__.py
fastsnmp/mass_resolver.py
fastsnmp/snmp_parser.c
fastsnmp/snmp_parser.pyx
fastsnmp/snmp_poller.py
fastsnmp.egg-info/PKG-INFO
fastsnmp.egg-info/SOURCES.txt
fastsnmp.egg-info/dependency_links.txt
fastsnmp.egg-info/top_level.txt
tests/tests.py