Metadata-Version: 2.4
Name: fastsnmp
Version: 0.16
Summary: SNMP poller oriented to poll bunch of hosts in short time. Package include poller and SNMP library
Home-page: https://github.com/gescheit/fastsnmp
Author: Aleksandr Balezin
Author-email: gescheit12@gmail.com
License: MIT
Keywords: SNMP poller parser library coder decoder
Platform: Linux
Classifier: Development Status :: 4 - Beta
Classifier: Operating System :: POSIX :: Linux
Classifier: License :: OSI Approved :: MIT License
Classifier: Programming Language :: Python :: 3 :: Only
Classifier: Topic :: System :: Networking :: Monitoring
Requires: Cython
License-File: LICENSE
Dynamic: author
Dynamic: author-email
Dynamic: classifier
Dynamic: description
Dynamic: description-content-type
Dynamic: home-page
Dynamic: keywords
Dynamic: license
Dynamic: license-file
Dynamic: platform
Dynamic: requires
Dynamic: summary
